deres/__init__.py
deres/deres.py
deres-0.1.1.dist-info/METADATA
deres-0.1.1.dist-info/WHEEL
deres-0.1.1.dist-info/licenses/LICENSE
deres-0.1.1.dist-info/RECORD
