Metadata-Version: 2.4
Name: deres
Version: 0.1.1
Summary: Container and visualization functions for differential expression (and similar) result tables.
Project-URL: Documentation, https://deres.readthedocs.io/
Project-URL: Homepage, https://github.com/scverse/deres
Project-URL: Source, https://github.com/scverse/deres
Author: Gregor Sturm
Maintainer-email: Gregor Sturm <gregor.sturm@scverse.org>
License: BSD 3-Clause License
License-File: LICENSE
Classifier: Programming Language :: Python :: 3 :: Only
Classifier: Programming Language :: Python :: 3.10
Classifier: Programming Language :: Python :: 3.11
Classifier: Programming Language :: Python :: 3.12
Classifier: Programming Language :: Python :: 3.13
Requires-Python: >=3.10
Requires-Dist: adjusttext
Requires-Dist: matplotlib
Requires-Dist: pandas>=2.2.3
Requires-Dist: seaborn
Requires-Dist: statsmodels>=0.14.4
Provides-Extra: dev
Requires-Dist: anndata; extra == 'dev'
Requires-Dist: pre-commit; extra == 'dev'
Requires-Dist: twine>=4.0.2; extra == 'dev'
Provides-Extra: doc
Requires-Dist: docutils!=0.18.*,!=0.19.*,>=0.8; extra == 'doc'
Requires-Dist: formulaic>=1.1.1; extra == 'doc'
Requires-Dist: ipykernel; extra == 'doc'
Requires-Dist: ipython; extra == 'doc'
Requires-Dist: myst-nb>=1.1; extra == 'doc'
Requires-Dist: nbconvert; extra == 'doc'
Requires-Dist: pandas; extra == 'doc'
Requires-Dist: pertpy; extra == 'doc'
Requires-Dist: pydeseq2; extra == 'doc'
Requires-Dist: scanpy; extra == 'doc'
Requires-Dist: setuptools; extra == 'doc'
Requires-Dist: sphinx-autodoc-typehints; extra == 'doc'
Requires-Dist: sphinx-book-theme>=1; extra == 'doc'
Requires-Dist: sphinx-copybutton; extra == 'doc'
Requires-Dist: sphinx-tabs; extra == 'doc'
Requires-Dist: sphinx>=4; extra == 'doc'
Requires-Dist: sphinxcontrib-bibtex>=1; extra == 'doc'
Requires-Dist: sphinxext-opengraph; extra == 'doc'
Requires-Dist: statsmodels; extra == 'doc'
Provides-Extra: stats
Provides-Extra: test
Requires-Dist: coverage; extra == 'test'
Requires-Dist: pytest; extra == 'test'
